Workbook

Sheet 調査サマリー
A1: Claude Agent SDK ドキュメント調査一覧
A3: 対象URL | B3: https://code.claude.com/docs/ja/agent-sdk/overview
A4: 調査日 | B4: 2026-07-24
A5: 対象範囲 | B5: 左側メニュー「Agent SDK」配下の全30ページ。本文中の実質的な参照リンク・関連ドキュメントも整理。
A6: 除外範囲 | B6: 共通ナビゲーション、言語切替、SNS、会社情報、フッター、ページ評価UI、同一ページ内アンカーの反復。
A7: メニューページ数 | B7: =COUNTA('メニュー別要約'!C:C)-1 | C7: ページ
A8: 機能明細数 | B8: =COUNTA('機能明細'!D:D)-1 | C8: 件
A9: 参照リンク数 | B9: =COUNTA('参照リンク'!D:D)-1 | C9: 件
A12: カテゴリ別ページ数
A13: Agent SDK | B13: =COUNTIF('メニュー別要約'!B:B,A13) | C13: ページ
A14: コアコンセプト | B14: =COUNTIF('メニュー別要約'!B:B,A14) | C14: ページ
A15: 入力と出力 | B15: =COUNTIF('メニュー別要約'!B:B,A15) | C15: ページ
A16: ツールで拡張 | B16: =COUNTIF('メニュー別要約'!B:B,A16) | C16: ページ
A17: 動作をカスタマイズ | B17: =COUNTIF('メニュー別要約'!B:B,A17) | C17: ページ
A18: 制御と可観測性 | B18: =COUNTIF('メニュー別要約'!B:B,A18) | C18: ページ
A19: デプロイメント | B19: =COUNTIF('メニュー別要約'!B:B,A19) | C19: ページ
A20: SDK リファレンス | B20: =COUNTIF('メニュー別要約'!B:B,A20) | C20: ページ
A22: 利用方法：まず「メニュー別要約」でページ単位の全体像を確認し、「機能明細」で個別機能を絞り込みます。「参照リンク」には参照元ページ、リンク先概要、リンク先が提供する機能・役割を記載しています。

Sheet メニュー別要約
A1: 左側メニュー別：概要・主要機能
A2: No. | B2: カテゴリ | C2: 左メニュー名 | D2: ページ概要 | E2: 主要機能（要約） | F2: 重要な注意点・制約 | G2: ページURL | H2: 参照リンク件数 | I2: 調査日
A3: 1 | B3: Agent SDK | C3: Agent SDK の概要 | D3: Claude Code をライブラリとして利用し、ファイル操作・コマンド実行・Web検索・コード編集を自律的に行う本番向けAIエージェントをPython/TypeScriptで構築するための全体像。組み込みツール、Hooks、サブエージェント、MCP、権限、セッションなどを俯瞰し、他のClaude開発手段との違いも説明する。 | E3: ・組み込みツール：Read/Write/Edit/Bash/Monitor/Glob/Grep/WebSearch/WebFetch/AskUserQuestionを利用できる。 ・エージェントループ：モデル判断→ツール実行→結果観察をタスク完了までSDKが反復する。 ・Hooks：ライフサイクルイベントで検証・ログ・ブロック・変換を行う。 ・サブエージェント：専門エージェントへ処理を委譲し、コンテキスト分離や並列化を行う。 ・MCP連携：外部DB、ブラウザ、API、SaaS等をMCP経由で接続する。 ・権限管理：allowedTools、拒否ルール、permissionMode、canUseTool等で操作を制御する。 ・セッション：会話・ツール履歴を保持し、resume、continue、forkを行う。 ・Claude Code設定資産の利用：CLAUDE.md、Skills、Commands、PluginsをSDKへ読み込む。 | F3: Agent SDKはツールループ実装済みのライブラリ。Client SDKはツール実行ループを利用者が実装する。Managed AgentsはAnthropic管理基盤で実行される。 | G3: https://code.claude.com/docs/ja/agent-sdk/overview | H3: =COUNTIF('参照リンク'!B:B,C3) | I3: 2026-07-24
A4: 2 | B4: Agent SDK | C4: クイックスタート | D4: SDKのインストール、APIキー設定、バグを含むサンプルファイル作成、Read/Edit/Globを使った自動修正エージェントの実行までを段階的に説明する入門ページ。 | E4: ・環境構築：Node.js 18+またはPython 3.10+でプロジェクトを作成する。 ・SDKインストール：TypeScriptまたはPythonパッケージを導入する。 ・認証：ANTHROPIC_API_KEYまたはBedrock/AWS/Google Cloud/Microsoft Foundryを設定する。 ・自動バグ修正：query()でファイルを読ませ、問題を発見・編集させる。 ・リアルタイム進捗：AssistantMessageとResultMessageを処理して推論・ツール・完了を表示する。 ・Web検索追加：WebSearchをallowedToolsへ追加する。 ・システムプロンプト設定：役割・品質基準・スタイルをカスタム設定する。 ・Bash実行：テスト実行やコマンド操作を許可する。 | F4: APIキーは実行プロセスの環境変数から読む。claude.aiログインを第三者製品の認証として提供する方式は原則不可。 | G4: https://code.claude.com/docs/ja/agent-sdk/quickstart | H4: =COUNTIF('参照リンク'!B:B,C4) | I4: 2026-07-24
A5: 3 | B5: コアコンセプト | C5: エージェントループの仕組み | D5: SDK内部のメッセージライフサイクル、ターン、ツール実行、コンテキストウィンドウ、セッション、結果メッセージ、Hooksを説明し、エージェントの動作を設計・デバッグする基礎を示す。 | E5: ・ループ制御：プロンプト受信、モデル評価、ツール実行、結果返却を反復する。 ・メッセージ型：SystemMessage、AssistantMessage、UserMessage、ResultMessage等を処理する。 ・組み込みツール実行：SDKが要求されたツールを実行し結果をClaudeへ戻す。 ・並列ツール実行：独立したツール呼び出しを並列処理できる。 ・ターン・予算制御：最大ターン、予算、努力レベル、モデルを設定する。 ・コンテキスト管理：ツール定義・会話・ファイル内容の消費量を管理し自動圧縮する。 ・セッション継続：同じ履歴を継続・再開・分岐する。 ・結果処理：最終テキスト、利用量、コスト、セッションIDをResultMessageから取得する。 | F5: SDKはCLIと同じ実行ループを子プロセスで動かす。コンテキスト消費と権限の設計が品質・コスト・安全性を左右する。 | G5: https://code.claude.com/docs/ja/agent-sdk/agent-loop | H5: =COUNTIF('参照リンク'!B:B,C5) | I5: 2026-07-24
A6: 4 | B6: コアコンセプト | C6: Claude Code 機能を使用する | D6: SDKからCLAUDE.md、ルール、Skills、Hooks、コマンド、エージェントなどClaude Codeのファイルシステム設定を読み込む方法と、settingSourcesによる読み込み範囲の制御を説明する。 | E6: ・設定ソース制御：user/project/local設定を読み込むか明示指定する。 ・CLAUDE.md読込：プロジェクト指示や規約をエージェントへ適用する。 ・Rules読込：パスや条件に応じたプロジェクトルールを適用する。 ・Skills読込：専門手順をSKILL.mdから検出する。 ・Hooks読込：設定ファイルのシェルフックとSDKコールバックを利用する。 ・Agents/Commands読込：サブエージェントとレガシーコマンドをファイルから利用する。 ・分離実行：CIやマルチテナントでローカル設定を除外する。 | F6: settingSourcesで制御できない管理設定や一部グローバル設定がある。デプロイ環境では明示的な読み込み範囲を推奨。 | G6: https://code.claude.com/docs/ja/agent-sdk/claude-code-features | H6: =COUNTIF('参照リンク'!B:B,C6) | I6: 2026-07-24
A7: 5 | B7: コアコンセプト | C7: セッションの操作 | D7: 会話履歴をディスクに保存し、最新会話の継続、特定IDの再開、元履歴を保った分岐を行う方法を説明する。PythonのClaudeSDKClientとTypeScriptのcontinueも扱う。 | E7: ・自動セッション管理：同一プロセスのマルチターン会話を自動追跡する。 ・セッションID取得：initまたはresultメッセージからIDを取得する。 ・Continue：現在の作業ディレクトリで最新セッションを継続する。 ・Resume：指定セッションIDを継続する。 ・Fork：履歴コピーから新セッションを作り代替案を試す。 ・ホスト間再開：共有ストレージまたはトランスクリプト同期で別ホストから再開する。 ・非永続セッション：TypeScriptでディスク保存を無効化する。 | F7: セッションは会話履歴を保持するが、ファイルシステムのスナップショットではない。ファイル復元はcheckpointingを使用する。 | G7: https://code.claude.com/docs/ja/agent-sdk/sessions | H7: =COUNTIF('参照リンク'!B:B,C7) | I7: 2026-07-24
A8: 6 | B8: コアコンセプト | C8: セッションを外部ストレージに永続化する | D8: ローカルJSONLトランスクリプトをS3、Redis、DB等へミラーし、任意のホストからセッションを再開するSessionStoreアダプターを説明する。 | E8: ・SessionStore：append/load必須、list/delete/listSubkeys任意のストレージIFを実装する。 ・外部ミラーリング：トランスクリプトを共有バックエンドへ保存する。 ・セッション読込：resume前に外部ストレージから履歴を復元する。 ・マルチホスト対応：サーバーレス/オートスケール/CI間で履歴を共有する。 ・保持・削除：保持期限・削除・一覧を独自ポリシーで管理する。 ・サブエージェント履歴：subpathでサブエージェントトランスクリプトを扱う。 ・圧縮後チェーン：getSessionMessagesは圧縮後の有効チェーンを返す。 | F8: SDKはローカルにも書くデュアルライト。外部ストア障害時の再試行・監視・整合性設計が必要。 | G8: https://code.claude.com/docs/ja/agent-sdk/session-storage | H8: =COUNTIF('参照リンク'!B:B,C8) | I8: 2026-07-24
A9: 7 | B9: 入力と出力 | C9: ストリーミング入力 | D9: エージェントへの入力方式として、長時間接続するストリーミング入力と、1回の文字列プロンプトを送るシングルメッセージ入力を比較する。 | E9: ・ストリーミング入力：AsyncIterable/AsyncGeneratorで複数メッセージを順次送信する。 ・画像入力：テキストとbase64画像を同じメッセージで送る。 ・メッセージキュー：ユーザー入力やイベントを待ちながら追加メッセージを送る。 ・割り込み・承認：実行中の入力、権限要求、確認質問を処理する。 ・コンテキスト永続：複数ターンで自然に会話履歴を保持する。 ・シングルメッセージ：文字列プロンプトを1回送信し、必要ならresumeで続ける。 ・用途選択：チャット/UIはストリーミング、バッチ/CIは単発入力を選ぶ。 | F9: 入力ストリーミングと出力の部分メッセージストリーミングは別設定。単発入力は割り込み等の機能が限定される。 | G9: https://code.claude.com/docs/ja/agent-sdk/streaming-vs-single-mode | H9: =COUNTIF('参照リンク'!B:B,C9) | I9: 2026-07-24
A10: 8 | B10: 入力と出力 | C10: 承認とユーザー入力を処理する | D10: ツール承認要求とAskUserQuestionによる確認質問を検出し、UIでユーザーへ提示してSDKへ許可・拒否・回答を返す方法を説明する。 | E10: ・入力要求検出：canUseToolコールバックでツール名と入力を受け取る。 ・ツール承認：許可、拒否、修正済み入力を返す。 ・AskUserQuestion：Claude生成の質問・選択肢をユーザーに表示する。 ・自由記述回答：選択肢に加えて任意テキストを受け付ける。 ・オプションプレビュー：TypeScriptで権限更新提案をUIへ表示する。 ・長時間保留：コールバック待機またはdeferで終了後にresumeする。 ・代替入力方法：ストリーミング入力や独自カスタムツールで入力を受ける。 | F10: PreToolUse Hookは全ツール呼び出しに適用可能。dontAskではユーザー対話が必要な呼び出しは拒否される。 | G10: https://code.claude.com/docs/ja/agent-sdk/user-input | H10: =COUNTIF('参照リンク'!B:B,C10) | I10: 2026-07-24
A11: 9 | B11: 入力と出力 | C11: リアルタイムでレスポンスをストリーミングする | D11: 部分メッセージを有効にし、テキストトークンやツール呼び出しの生成途中イベントを受け取ってリアルタイムUIを構築する方法を説明する。 | E11: ・部分メッセージ有効化：includePartialMessagesを有効にする。 ・StreamEvent処理：content_block_delta等のイベント型を分岐する。 ・テキスト差分：text_deltaを逐次表示する。 ・ツール呼び出し差分：tool_use入力の生成途中を可視化する。 ・メッセージフロー：partial→完成AssistantMessage→ResultMessageを扱う。 ・ストリーミングUI：進捗、ツール名、最終結果を状態管理する。 ・CLIストリーム：CLI経由のプログラム実行でも逐次出力を扱う。 | F11: 部分イベントは低レベルAPIイベント。最終的な完全メッセージと二重計上しないこと。 | G11: https://code.claude.com/docs/ja/agent-sdk/streaming-output | H11: =COUNTIF('参照リンク'!B:B,C11) | I11: 2026-07-24
A12: 10 | B12: 入力と出力 | C12: エージェントから構造化された出力を取得する | D12: JSON Schema、Zod、Pydanticで出力形状を指定し、複数ターンのツール実行後に検証済みJSONを取得する方法を説明する。 | E12: ・JSON Schema出力：出力スキーマをqueryへ渡し、結果を検証する。 ・自動再プロンプト：スキーマ不一致時にSDKが再試行する。 ・型安全なTypeScript：Zodから入力・出力型を得る。 ・型安全なPython：Pydanticモデルから検証済みオブジェクトを得る。 ・structured_output取得：ResultMessageの構造化フィールドを使用する。 ・アプリ連携：DB、UI、後続処理へ直接渡せる。 ・エラー処理：スキーマ違反・未完了・モデルエラーを区別する。 | F12: 構造化出力は形式を保証するが、内容の事実性や業務妥当性を保証しない。 | G12: https://code.claude.com/docs/ja/agent-sdk/structured-outputs | H12: =COUNTIF('参照リンク'!B:B,C12) | I12: 2026-07-24
A13: 11 | B13: ツールで拡張 | C13: Claude にカスタムツールを提供する | D13: インプロセスMCPサーバーを用いて独自関数をツール化し、API、DB、ドメインロジック、画像・リソース・構造化データをClaudeへ提供する方法を説明する。 | E13: ・ツール定義：名前・説明・入力スキーマ・非同期ハンドラーを定義する。 ・SDK MCPサーバー：複数ツールをインプロセスサーバーとして登録する。 ・アクセス制御：mcp__server__tool形式でallowedToolsへ追加する。 ・ツール注釈：readOnlyHint等で副作用特性を伝える。 ・エラー返却：isErrorと説明文でモデルへ回復可能なエラーを返す。 ・画像返却：base64画像コンテンツを結果として返す。 ・リソース返却：URI・MIME・内容をresourceブロックで返す。 ・構造化データ：structuredContentで機械可読結果を返す。 ・ツール検索対応：大量ツールはオンデマンド検索させる。 | F13: ツールハンドラーはアプリプロセス内で実行されるため、認証・入力検証・タイムアウト・監査を実装する。 | G13: https://code.claude.com/docs/ja/agent-sdk/custom-tools | H13: =COUNTIF('参照リンク'!B:B,C13) | I13: 2026-07-24
A14: 12 | B14: ツールで拡張 | C14: MCP を使用して外部ツールに接続する | D14: MCPサーバーをコードまたは.mcp.jsonで設定し、stdio/HTTP/SSE/SDK内蔵トランスポート、ツール許可、認証、検索、エラー処理を行う方法を説明する。 | E14: ・サーバー設定：mcpServersまたは.mcp.jsonで接続先を定義する。 ・ツール命名：mcp__<server>__<tool>形式で識別する。 ・ツール許可：個別またはサーバー単位でallowedToolsへ追加する。 ・stdio：ローカルプロセスをstdin/stdoutで接続する。 ・HTTP/SSE：リモートサーバーへURL・ヘッダーで接続する。 ・SDK MCP：アプリ内のカスタムツールを接続する。 ・ツール検索：多数ツールを必要時だけロードする。 ・認証：env、HTTPヘッダー、OAuthアクセストークンを渡す。 ・接続状態検査：initメッセージのmcp_servers状態を確認する。 ・エラー処理：失敗、未呼出、タイムアウト、出力上限を診断する。 | F14: MCPツールは明示許可が必要。資格情報はコードやログへ直書きせず、最小権限のトークンを利用する。 | G14: https://code.claude.com/docs/ja/agent-sdk/mcp | H14: =COUNTIF('参照リンク'!B:B,C14) | I14: 2026-07-24
... A32: 30 | B32: SDK リファレンス | C32: 移行ガイド | D32: 旧Claude Code SDKからClaude Agent SDKへのパッケージ名・import・型名変更と、システムプロンプト・設定ソースの破壊的変更を説明する。 | E32: ・TSパッケージ移行：@anthropic-ai/claude-codeをagent-sdkへ置換する。 ・Pythonパッケージ移行：claude-code-sdkをclaude-agent-sdkへ置換する。 ・Import更新：旧モジュールパスを新パスへ変更する。 ・型名変更：ClaudeCodeOptionsをClaudeAgentOptionsへ変更する。 ・システムプロンプト変更：既定が最小プロンプトになったため必要ならclaude_code presetを指定する。 ・設定ソース：現在は省略時にuser/project/localを読み込む。分離時は[]を指定。 ・テスト：権限・ツール・出力・セッション動作を回帰確認する。 ・ブランド/目的：コーディング以外の汎用エージェント基盤として名称変更された。 | F32: パッケージ名だけでなくデフォルトのシステムプロンプトが変わる。移行後の品質・安全性・設定混入を回帰テストする。 | G32: https://code.claude.com/docs/ja/agent-sdk/migration-guide | H32: =COUNTIF('参照リンク'!B:B,C32) | I32: 2026-07-24

Sheet 機能明細
A1: 左側メニュー別：機能明細
A2: No. | B2: カテゴリ | C2: 左メニュー名 | D2: 機能名 | E2: 機能概要 | F2: 主なAPI・設定・要素 | G2: 制約・注意点 | H2: ページURL
A3: 1 | B3: Agent SDK | C3: Agent SDK の概要 | D3: 組み込みツール | E3: Read/Write/Edit/Bash/Monitor/Glob/Grep/WebSearch/WebFetch/AskUserQuestionを利用できる。 | F3: allowed_tools / allowedTools | G3: ツールごとに権限設計が必要。 | H3: https://code.claude.com/docs/ja/agent-sdk/overview
A4: 2 | B4: Agent SDK | C4: Agent SDK の概要 | D4: エージェントループ | E4: モデル判断→ツール実行→結果観察をタスク完了までSDKが反復する。 | F4: query() | G4: ターン数・予算・権限の上限を設定する。 | H4: https://code.claude.com/docs/ja/agent-sdk/overview
A5: 3 | B5: Agent SDK | C5: Agent SDK の概要 | D5: Hooks | E5: ライフサイクルイベントで検証・ログ・ブロック・変換を行う。 | F5: hooks | G5: イベントとマッチャーの設計が必要。 | H5: https://code.claude.com/docs/ja/agent-sdk/overview
A6: 4 | B6: Agent SDK | C6: Agent SDK の概要 | D6: サブエージェント | E6: 専門エージェントへ処理を委譲し、コンテキスト分離や並列化を行う。 | F6: agents / AgentDefinition | G6: Agentツールの許可が必要。 | H6: https://code.claude.com/docs/ja/agent-sdk/overview
A7: 5 | B7: Agent SDK | C7: Agent SDK の概要 | D7: MCP連携 | E7: 外部DB、ブラウザ、API、SaaS等をMCP経由で接続する。 | F7: mcpServers | G7: 接続先認証とツール許可を分離して管理する。 | H7: https://code.claude.com/docs/ja/agent-sdk/overview
A8: 6 | B8: Agent SDK | C8: Agent SDK の概要 | D8: 権限管理 | E8: allowedTools、拒否ルール、permissionMode、canUseTool等で操作を制御する。 | F8: permissionMode / canUseTool | G8: bypassPermissionsは隔離環境向け。 | H8: https://code.claude.com/docs/ja/agent-sdk/overview
A9: 7 | B9: Agent SDK | C9: Agent SDK の概要 | D9: セッション | E9: 会話・ツール履歴を保持し、resume、continue、forkを行う。 | F9: resume / continue / forkSession | G9: ファイル状態は別途checkpointingで管理。 | H9: https://code.claude.com/docs/ja/agent-sdk/overview
A10: 8 | B10: Agent SDK | C10: Agent SDK の概要 | D10: Claude Code設定資産の利用 | E10: CLAUDE.md、Skills、Commands、PluginsをSDKへ読み込む。 | F10: settingSources | G10: ローカル設定の意図しない混入に注意。 | H10: https://code.claude.com/docs/ja/agent-sdk/overview
A11: 9 | B11: Agent SDK | C11: クイックスタート | D11: 環境構築 | E11: Node.js 18+またはPython 3.10+でプロジェクトを作成する。 | F11: npm / uv / pip | G11: Pythonは仮想環境推奨。 | H11: https://code.claude.com/docs/ja/agent-sdk/quickstart
A12: 10 | B12: Agent SDK | C12: クイックスタート | D12: SDKインストール | E12: TypeScriptまたはPythonパッケージを導入する。 | F12: @anthropic-ai/claude-agent-sdk / claude-agent-sdk | G12: TSはネイティブCLIバイナリを同梱。 | H12: https://code.claude.com/docs/ja/agent-sdk/quickstart
A13: 11 | B13: Agent SDK | C13: クイックスタート | D13: 認証 | E13: ANTHROPIC_API_KEYまたはBedrock/AWS/Google Cloud/Microsoft Foundryを設定する。 | F13: 環境変数 | G13: SDKは.envを自動読込しない。 | H13: https://code.claude.com/docs/ja/agent-sdk/quickstart
A14: 12 | B14: Agent SDK | C14: クイックスタート | D14: 自動バグ修正 | E14: query()でファイルを読ませ、問題を発見・編集させる。 | F14: query(), ClaudeAgentOptions | G14: Read/Edit/Globを事前承認する例。 | H14: https://code.claude.com/docs/ja/agent-sdk/quickstart
... A247: 245 | B247: SDK リファレンス | C247: 移行ガイド | D247: ブランド/目的 | E247: コーディング以外の汎用エージェント基盤として名称変更された。 | F247: documentation | G247: 新ドキュメント構成を参照。 | H247: https://code.claude.com/docs/ja/agent-sdk/migration-guide

Sheet 参照リンク
A1: 本文リンク・関連参照：概要・機能一覧
A2: No. | B2: 参照元メニュー | C2: カテゴリ | D2: 参照先タイトル | E2: 参照区分 | F2: 参照先URL | G2: 参照先の概要 | H2: 参照先の機能・役割 | I2: 参照文脈
A3: 1 | B3: Agent SDK の概要 | C3: Agent SDK | D3: クイックスタート | E3: Agent SDK内メニュー | F3: https://code.claude.com/docs/ja/agent-sdk/quickstart | G3: SDKのインストール、APIキー設定、バグを含むサンプルファイル作成、Read/Edit/Globを使った自動修正エージェントの実行までを段階的に説明する入門ページ。 | H3: 導入手順へ進む | I3: 関連ドキュメント
A4: 2 | B4: Agent SDK の概要 | C4: Agent SDK | D4: エージェントループの仕組み | E4: Agent SDK内メニュー | F4: https://code.claude.com/docs/ja/agent-sdk/agent-loop | G4: SDK内部のメッセージライフサイクル、ターン、ツール実行、コンテキストウィンドウ、セッション、結果メッセージ、Hooksを説明し、エージェントの動作を設計・デバッグする基礎を示す。 | H4: 自律ループの内部を理解する | I4: 関連ドキュメント
A5: 3 | B5: Agent SDK の概要 | C5: Agent SDK | D5: MCP を使用して外部ツールに接続する | E5: Agent SDK内メニュー | F5: https://code.claude.com/docs/ja/agent-sdk/mcp | G5: MCPサーバーをコードまたは.mcp.jsonで設定し、stdio/HTTP/SSE/SDK内蔵トランスポート、ツール許可、認証、検索、エラー処理を行う方法を説明する。 | H5: 外部システム連携を拡張する | I5: 関連ドキュメント
A6: 4 | B6: Agent SDK の概要 | C6: Agent SDK | D6: パーミッションの設定 | E6: Agent SDK内メニュー | F6: https://code.claude.com/docs/ja/agent-sdk/permissions | G6: Hook、deny/ask/allowルール、permissionMode、canUseToolの評価順を示し、ツール利用の自動許可・拒否・対話承認を設計する。 | H6: 安全なツール利用を設計する | I6: 関連ドキュメント
A7: 5 | B7: Agent SDK の概要 | C7: Agent SDK | D7: セッションの操作 | E7: Agent SDK内メニュー | F7: https://code.claude.com/docs/ja/agent-sdk/sessions | G7: 会話履歴をディスクに保存し、最新会話の継続、特定IDの再開、元履歴を保った分岐を行う方法を説明する。PythonのClaudeSDKClientとTypeScriptのcontinueも扱う。 | H7: 会話継続・再開を実装する | I7: 関連ドキュメント
A8: 6 | B8: Agent SDK の概要 | C8: Agent SDK | D8: Claude Developer Platform | E8: 公式プラットフォーム | F8: https://platform.claude.com/ | G8: APIキー、モデル、利用状況、開発者向けリソースを提供する。 | H8: Agent SDKの認証・モデル利用の基盤。 | I8: 本文参照
A9: 7 | B9: Agent SDK の概要 | C9: Agent SDK | D9: Agent SDK ドキュメント索引（llms.txt） | E9: 公式索引 | F9: https://code.claude.com/docs/llms.txt | G9: Claude Codeドキュメント全ページのタイトル・URL・短い説明を機械可読形式で提供する。 | H9: 対象ページや関連ページの発見に使用。 | I9: 本文参照
A10: 8 | B10: クイックスタート | C10: Agent SDK | D10: TypeScript SDK | E10: Agent SDK内メニュー | F10: https://code.claude.com/docs/ja/agent-sdk/typescript | G10: TypeScript版Agent SDKの完全APIリファレンス。query()、Options、メッセージ型、Hooks、カスタムツール、MCP、セッション、SessionStore、エラー型などを定義する。 | H10: TypeScript API詳細を確認 | I10: 関連ドキュメント
A11: 9 | B11: クイックスタート | C11: Agent SDK | D11: Python SDK | E11: Agent SDK内メニュー | F11: https://code.claude.com/docs/ja/agent-sdk/python | G11: Python版Agent SDKの完全APIリファレンス。query()とClaudeSDKClient、ClaudeAgentOptions、メッセージ/コンテンツ型、Hooks、カスタムツール、MCP、Transport、例外などを定義する。 | H11: Python API詳細を確認 | I11: 関連ドキュメント
A12: 10 | B12: クイックスタート | C12: Agent SDK | D12: ストリーミング入力 | E12: Agent SDK内メニュー | F12: https://code.claude.com/docs/ja/agent-sdk/streaming-vs-single-mode | G12: エージェントへの入力方式として、長時間接続するストリーミング入力と、1回の文字列プロンプトを送るシングルメッセージ入力を比較する。 | H12: 入力方式を選ぶ | I12: 関連ドキュメント
A13: 11 | B13: クイックスタート | C13: Agent SDK | D13: Agent SDK のホスティング | E13: Agent SDK内メニュー | F13: https://code.claude.com/docs/ja/agent-sdk/hosting | G13: SDKがclaude CLI子プロセスを起動しローカル作業ディレクトリとセッション状態を持つ前提で、Docker/Kubernetes/サンドボックス、永続化、スケール、監視、マルチテナント分離を設計する。 | H13: 本番デプロイへ進む | I13: 関連ドキュメント
A14: 12 | B14: クイックスタート | C14: Agent SDK | D14: tsx | E14: 外部ツール | F14: https://tsx.is/ | G14: TypeScript/ESMファイルをビルド手順なしで直接実行するランナー。 | H14: クイックスタートのTSスクリプト実行。 | I14: 本文参照
... A129: 127 | B129: 移行ガイド | C129: SDK リファレンス | D129: Claude Code 機能を使用する | E129: Agent SDK内メニュー | F129: https://code.claude.com/docs/ja/agent-sdk/claude-code-features | G129: SDKからCLAUDE.md、ルール、Skills、Hooks、コマンド、エージェントなどClaude Codeのファイルシステム設定を読み込む方法と、settingSourcesによる読み込み範囲の制御を説明する。 | H129: settingSourcesの現行挙動 | I129: 関連ドキュメント

Sheet 調査条件
A1: 調査条件・読み方・留意事項
A2: 項目 | B2: 内容
A3: 対象の定義 | B3: 2026-07-24時点で、指定ページの左側ナビゲーション「Agent SDK」配下に表示される30メニューを対象としました。
A4: ページ要約の作成方法 | B4: 公式日本語ドキュメントのページタイトル、導入文、目次、主要説明、表・注意事項をもとに、日本語で圧縮要約しました。コード例はAPI/設定名へ抽象化しています。
A5: 機能の列挙方法 | B5: 各ページで説明される機能、設定、ワークフロー、制御点を1行1機能で分解しました。ページ内のすべてのコード行や全型プロパティを逐語的に転記したものではありません。
A6: 参照リンクの範囲 | B6: 本文中の実質的な参照先、関連ドキュメント、標準、パッケージ、公式プラットフォームを対象とし、共通ナビゲーション、SNS、会社情報、フッター、ページ内アンカーの反復は除外しました。
A7: 参照先の概要・機能 | B7: リンク先そのものの役割を短く要約し、参照元ページから見た利用目的を「参照先の機能・役割」に記載しました。再帰的にリンク先の全リンクを無制限に追跡する方式ではありません。
A8: 公式性 | B8: 一次情報であるcode.claude.com、platform.claude.com、公式標準・パッケージページを優先しています。
A9: 更新注意 | B9: Agent SDKは更新頻度が高く、API名、既定値、バージョン要件、対応モデルは変更される可能性があります。実装時は各行のURLで最新版を確認してください。
A10: TypeScript V2 | B10: 「TypeScript V2（削除済み）」はサポート終了した旧APIの保守・移行用ページです。新規実装では現行query() APIを利用します。
A11: Todo/Task | B11: Todoページは旧TodoWriteから現行Taskツールへの移行情報を含みます。SDK/CLIのバージョンにより観測するツール名が異なります。
A12: コスト | B12: SDKのコストフィールドはクライアント側推定値です。正式な請求・財務判断にはClaude PlatformのUsage and Cost API/Consoleを利用します。
A13: セキュリティ | B13: 権限やHooksだけでなく、コンテナ/VM、読み取り専用マウント、ネットワーク制御、短命資格情報などを組み合わせる前提で整理しています。
